setup.cfg
setup.py
src/vial/__init__.py
src/vial/meta.py
src/vial/session.py
vial.egg-info/PKG-INFO
vial.egg-info/SOURCES.txt
vial.egg-info/dependency_links.txt
vial.egg-info/requires.txt
vial.egg-info/top_level.txt